hoom/__init__.py
hoom/accessory_types/Lightbulb.py
hoom/accessory_types/Switch.py
hoom/accessory_types/TemperatureSensor.py
hoom/accessory_types/__init__.py
hoom/bridge.py
hoom/exceptions/AccessoryExceptions.py
hoom/exceptions/__init__.py
hoom/pages/assets/bootstrap/css/bootstrap.min.css
hoom/pages/assets/bootstrap/js/bootstrap.min.js
hoom/pages/assets/img/error.png
hoom/pages/assets/js/jquery.min.js
hoom/pages/assets/js/qrcode.min.js
hoom/pages/connect.html
hoom-0.1.6.dist-info/LICENSE
hoom-0.1.6.dist-info/METADATA
hoom-0.1.6.dist-info/WHEEL
hoom-0.1.6.dist-info/RECORD
