Metadata-Version: 2.1
Name: hoom
Version: 0.1.6
Summary: Build your own HomeKit Bridge & Accessories with Hoom
Home-page: https://berrysauce.me/hoom
License: GPL-3.0-only
Author: Paul Haedrich
Author-email: hey@foerstal.com
Requires-Python: >=3.8,<4.0
Classifier: License :: OSI Approved :: GNU General Public License v3 (GPLv3)
Classifier: Programming Language :: Python :: 3
Classifier: Programming Language :: Python :: 3.8
Classifier: Programming Language :: Python :: 3.9
Classifier: Programming Language :: Python :: 3.10
Classifier: Programming Language :: Python :: 3.11
Classifier: Programming Language :: Python :: 3 :: Only
Classifier: Topic :: Home Automation
Classifier: Topic :: Software Development
Classifier: Topic :: Utilities
Requires-Dist: base36 (>=0.1.1,<0.2.0)
Requires-Dist: colorama (>=0.4.6,<0.5.0)
Requires-Dist: fastapi (>=0.100.0,<0.101.0)
Requires-Dist: hap-python (>=4.7.0,<5.0.0)
Requires-Dist: jinja2 (>=3.1.2,<4.0.0)
Requires-Dist: pyqrcode (>=1.2.1,<2.0.0)
Requires-Dist: uvicorn (>=0.23.1,<0.24.0)
Project-URL: Documentation, https://berrysauce.me/hoom
Project-URL: Repository, https://github.com/berrysauce/hoom
